hello_poetry/__init__.py
hello_poetry/main.py
hello_poetry-0.1.0.dist-info/METADATA
hello_poetry-0.1.0.dist-info/WHEEL
hello_poetry-0.1.0.dist-info/RECORD
